eb_examples/__init__.py
eb_examples/__main__.py
eb_examples/cli.py
eb_examples/paths.py
eb_examples/datasets/__init__.py
eb_examples/datasets/demo_golden_v1.py
eb_examples-0.2.0.dist-info/licenses/LICENSE
eb_examples-0.2.0.dist-info/METADATA
eb_examples-0.2.0.dist-info/WHEEL
eb_examples-0.2.0.dist-info/entry_points.txt
eb_examples-0.2.0.dist-info/top_level.txt
eb_examples-0.2.0.dist-info/RECORD
